Metadata-Version: 1.0
Name: s2pyStats
Version: 0.1
Summary: Get Stats of Users!
Home-page: UNKNOWN
Author: Knightbot63
Author-email: UNKNOWN
License: UNKNOWN
Platform: UNKNOWN
